numpyextra.py
numpyextra-1.1.0.dist-info/LICENSE
numpyextra-1.1.0.dist-info/METADATA
numpyextra-1.1.0.dist-info/WHEEL
numpyextra-1.1.0.dist-info/top_level.txt
numpyextra-1.1.0.dist-info/RECORD
