Metadata-Version: 2.1
Name: numpyextra
Version: 1.1.0
Summary: Supplement NumPy.
Author-email: John Dawson <john.a.dawson@proton.me>
Maintainer-email: John Dawson <john.a.dawson@proton.me>
License:                     GNU GENERAL PUBLIC LICENSE
Project-URL: Homepage, https://github.com/JohnADawson/numpyextra
Project-URL: Documentation, https://github.com/JohnADawson/numpyextra/blob/master/src/numpyextra.py
Keywords: gufunc,gufuncs,numpy
License-File: LICENSE
Requires-Dist: numpy
